{
  "id": "",
  "name": "",
  "font_family": "iconfont",
  "css_prefix_text": "icon-",
  "description": "",
  "glyphs": [
    {
      "icon_id": "4423232",
      "name": "评论",
      "font_class": "pinglun",
      "unicode": "e682",
      "unicode_decimal": 59010
    },
    {
      "icon_id": "6584468",
      "name": "赞",
      "font_class": "zan",
      "unicode": "e61f",
      "unicode_decimal": 58911
    },
    {
      "icon_id": "8033355",
      "name": "收 藏",
      "font_class": "shoucang",
      "unicode": "e501",
      "unicode_decimal": 58625
    }
  ]
}
